Workbook
Name Slicer_Year: #N/A
Name Slicer_Year1: #N/A
Name Slicer_Year2: #N/A

Sheet dfincome
A1: Year | B1: Month | C1: Income sources | D1: Income Breakdowns | E1: Counts | F1: Income | G1: Target Income | H1: operating profit | I1: Marketing Strategies
A2: 2020 | B2: Jan | C2: Licensing | D2: Software Metered License | E2: 3566 | F2: 5492.76 | G2: 5126.576 | H2: 1098.552 | I2: B2B
A3: 2020 | B3: Jan | C3: Licensing | D3: Floating License | E3: 2498 | F3: 9600 | G3: 8960 | H3: 1920 | I3: B2B
A4: 2020 | B4: Jan | C4: Renting | D4: Equipments | E4: 1245 | F4: 5492.64 | G4: 5126.464 | H4: 1098.528 | I4: B2B
A5: 2020 | B5: Jan | C5: Subscription | D5: Prime | E5: 644 | F5: 6892.2 | G5: 6432.72 | H5: 1378.44 | I5: B2B
A6: 2020 | B6: Jan | C6: Usage fees | D6: Renewal | E6: 643 | F6: 7700 | G6: 7840 | H6: 1540 | I6: B2B
A7: 2020 | B7: Jan | C7: Subscription | D7: Premium | E7: 455 | F7: 5265.39 | G7: 5128.032 | H7: 1053.078 | I7: B2B
A8: 2020 | B8: Jan | C8: Usage fees | D8: New | E8: 345 | F8: 9016 | G8: 7840 | H8: 1803.2 | I8: B2B
A9: 2020 | B9: Jan | C9: Renting | D9: Offices | E9: 122 | F9: 2696.75 | G9: 112 | H9: 539.35 | I9: B2B
A10: 2020 | B10: Jan | C10: Advertising | D10: Facebook Page | E10: 78 | F10: 5492.64 | G10: 5126.464 | H10: 1098.528 | I10: B2B
A11: 2020 | B11: Jan | C11: Advertising | D11: Google Ad | E11: 76 | F11: 5492.28 | G11: 5126.128 | H11: 1098.456 | I11: B2B
A12: 2020 | B12: Jan | C12: Advertising | D12: Company Website | E12: 46 | F12: 240 | G12: 224 | H12: 48 | I12: B2B
A13: 2020 | B13: Jan | C13: Advertising | D13: Youtube Channel | E13: 34 | F13: 5492.16 | G13: 5126.016 | H13: 1098.432 | I13: B2B
... A901: 2024 | B901: Dec | C901: Asset sale | D901: Asset sale | E901: 2 | F901: 6600 | G901: 7392 | H901: 1320 | I901: B2B
F903: =SUM(F2:F901) -> 3947317.7

Sheet ptincome
B2: Row Labels | C2: Sum of Income | D2: Sum of Counts | E2: Sum of Counts2 | G2: Column1 | H2: X | I2: Y | J2: Amount | K2: Max | L2: Without max | M2: Count | N2: Count % | P2: Sum of Income | Q2: Sum of Target Income | T2: Row Labels | U2: Sum of Income | V2: Sum of Income2
B3: Usage fees | C3: 177100 | D3: 11856 | E3: 0.10118631 | G3: Usage fees | H3: 1 | I3: 3 | J3: =VLOOKUP(G3, ptincome!B:D, 2, FALSE) -> 177100 | K3: =IF(J3=MAX($J$3:$J$8),J3," ") | L3: =IF(J3=MAX($J$3:$J$8)," ",J3) -> 177100 | M3: =VLOOKUP(G3, ptincome!B:E, 3, FALSE) -> 11856 | N3: =VLOOKUP(G3, ptincome!B:E, 4, FALSE) -> 0.10118631 | P3: 773252.33 | Q3: 898931.71 | T3: Jan | U3: 64934.67 | V3: 64934.67
B4: Subscription | C4: 182598.14 | D4: 13188 | E4: 0.11255441 | G4: Subscription | H4: 7 | I4: 2 | J4: =VLOOKUP(G4, ptincome!B:D, 2, FALSE) -> 182598.14 | K4: =IF(J4=MAX($J$3:$J$8),J4," ") -> 182598.14 | L4: =IF(J4=MAX($J$3:$J$8)," ",J4) | M4: =VLOOKUP(G4, ptincome!B:E, 3, FALSE) -> 13188 | N4: =VLOOKUP(G4, ptincome!B:E, 4, FALSE) -> 0.11255441 | P4: =GETPIVOTDATA("Sum of Income",$P$2) -> 773252.33 | Q4: =GETPIVOTDATA("Sum of Target Income",$P$2) -> 898931.71 | T4: Feb | U4: 58642.05 | V4: 58642.05
B5: Renting | C5: 61203.86 | D5: 16488 | E5: 0.14071861 | G5: Renting | H5: 4 | I5: 1 | J5: =VLOOKUP(G5, ptincome!B:D, 2, FALSE) -> 61203.86 | K5: =IF(J5=MAX($J$3:$J$8),J5," ") | L5: =IF(J5=MAX($J$3:$J$8)," ",J5) -> 61203.86 | M5: =VLOOKUP(G5, ptincome!B:E, 3, FALSE) -> 16488 | N5: =VLOOKUP(G5, ptincome!B:E, 4, FALSE) -> 0.14071861 | T5: Mar | U5: 61887.2 | V5: 61887.2
B6: Licensing | C6: 157387.39 | D6: 72768 | E6: 0.62104634 | G6: Licensing | H6: 2 | I6: 8 | J6: =VLOOKUP(G6, ptincome!B:D, 2, FALSE) -> 157387.39 | K6: =IF(J6=MAX($J$3:$J$8),J6," ") | L6: =IF(J6=MAX($J$3:$J$8)," ",J6) -> 157387.39 | M6: =VLOOKUP(G6, ptincome!B:E, 3, FALSE) -> 72768 | N6: =VLOOKUP(G6, ptincome!B:E, 4, FALSE) -> 0.62104634 | P6: Income | Q6: Target | T6: Apr | U6: 77628.6 | V6: 77628.6
B7: Asset sale | C7: 77421.9 | D7: 26 | E7: 0.0002218998 | G7: Advertising | H7: 6 | I7: 6 | J7: =VLOOKUP(G7, ptincome!B:D, 2, FALSE) -> 117541.05 | K7: =IF(J7=MAX($J$3:$J$8),J7," ") | L7: =IF(J7=MAX($J$3:$J$8)," ",J7) -> 117541.05 | M7: =VLOOKUP(G7, ptincome!B:E, 3, FALSE) -> 2844 | N7: =VLOOKUP(G7, ptincome!B:E, 4, FALSE) -> 0.024272425 | P7: =P3/Q3 -> 0.86019029 | Q7: =100%-P7 -> 0.13980971 | T7: May | U7: 60548.14 | V7: 60548.14
B8: Advertising | C8: 117541.05 | D8: 2844 | E8: 0.024272425 | G8: Asset sale | H8: 5 | I8: 9 | J8: =VLOOKUP(G8, ptincome!B:D, 2, FALSE) -> 77421.9 | K8: =IF(J8=MAX($J$3:$J$8),J8," ") | L8: =IF(J8=MAX($J$3:$J$8)," ",J8) -> 77421.9 | M8: =VLOOKUP(G8, ptincome!B:E, 3, FALSE) -> 26 | N8: =VLOOKUP(G8, ptincome!B:E, 4, FALSE) -> 0.0002218998 | T8: Jun | U8: 63285.9 | V8: 63285.9
B9: Grand Total | C9: 773252.33 | D9: 117170 | E9: 1 | T9: Jul | U9: 57630.7 | V9: 57630.7
T10: Aug | U10: 60977.822 | V10: 60977.822
T11: Sep | U11: 59906.11 | V11: 59906.11
T12: Oct | U12: 66177.665 | V12: 66177.665
T13: Nov | U13: 84002.775 | V13: 84002.775
T14: Dec | U14: 57630.7 | V14: 57630.7
T15: Grand Total | U15: 773252.33 | V15: 773252.33
G16: Row Labels | H16: Sum of Income | I16: Sum of Income2 | K16: Row Labels | L16: Sum of Income | M16: Sum of Income2 | P16: =G17 -> Usage fees | Q16: =H17 -> 177100 | R16: =I17 -> 0.22903261
B17: Row Labels | C17: Sum of operating profit | E17: Operative Profit | G17: Usage fees | H17: 177100 | I17: 0.22903261 | K17: B2B | L17: 261479.22 | M17: 0.3381551 | P17: =G18 -> New | Q17: =H18 -> 88900 | R17: =I18 -> 0.11496894 | V17: Average Monthly Income
B18: Jan | C18: 12986.934 | E18: =IFERROR(C30," ") -> 154650.47 | G18: New | H18: 88900 | I18: 0.11496894 | K18: B2C | L18: 511773.12 | M18: 0.6618449 | P18: =G19 -> Renewal | Q18: =H19 -> 88200 | R18: =I19 -> 0.11406367 | V18: =IFERROR(AVERAGE(U3:U14)," ") -> 64437.694
B19: Feb | C19: 11728.41 | G19: Renewal | H19: 88200 | I19: 0.11406367 | K19: Grand Total | L19: 773252.33 | M19: 1 | P19: =G20 -> Subscription | Q19: =H20 -> 182598.14 | R19: =I20 -> 0.23614301
B20: Mar | C20: 12377.44 | G20: Subscription | H20: 182598.14 | I20: 0.23614301 | P20: =G21 -> Premium | Q20: =H21 -> 77065.56 | R20: =I21 -> 0.09966418
B21: Apr | C21: 15525.72 | G21: Premium | H21: 77065.56 | I21: 0.09966418 | K21: B2B | L21: =IFERROR(L17,"") -> 261479.22 | M21: =IFERROR(M17,"") -> 0.3381551 | P21: =G22 -> Prime | Q21: =H22 -> 105532.57 | R21: =I22 -> 0.13647883
B22: May | C22: 12109.628 | G22: Prime | H22: 105532.57 | I22: 0.13647883 | K22: B2C | L22: =IFERROR(L18,"") -> 511773.12 | M22: =IFERROR(M18,"") -> 0.6618449 | P22: =G23 -> Renting | Q22: =H23 -> 61203.86 | R22: =I23 -> 0.079151213
B23: Jun | C23: 12657.18 | G23: Renting | H23: 61203.86 | I23: 0.079151213 | P23: =G24 -> Equipments | Q23: =H24 -> 57443.86 | R23: =I24 -> 0.074288635
B24: Jul | C24: 11526.14 | G24: Equipments | H24: 57443.86 | I24: 0.074288635 | P24: =G25 -> Lands | Q24: =H25 -> 2490 | R24: =I25 -> 0.0032201649
B25: Aug | C25: 12195.565 | G25: Lands | H25: 2490 | I25: 0.0032201649 | P25: =G26 -> Offices | Q25: =H26 -> 1270 | R25: =I26 -> 0.0016424134
B26: Sep | C26: 11981.222 | G26: Offices | H26: 1270 | I26: 0.0016424134 | P26: =G27 -> Licensing | Q26: =H27 -> 157387.39 | R26: =I27 -> 0.20353949
B27: Oct | C27: 13235.533 | G27: Licensing | H27: 157387.39 | I27: 0.20353949 | P27: =G28 -> Floating License | Q27: =H28 -> 100400 | R27: =I28 -> 0.12984119
B28: Nov | C28: 16800.555 | G28: Floating License | H28: 100400 | I28: 0.12984119 | P28: =G29 -> Software Metered License | Q28: =H29 -> 56987.385 | R28: =I29 -> 0.073698303
B29: Dec | C29: 11526.14 | G29: Software Metered License | H29: 56987.385 | I29: 0.073698303 | P29: =G30 -> Asset sale | Q29: =H30 -> 77421.9 | R29: =I30 -> 0.10012501
B30: Grand Total | C30: 154650.47 | G30: Asset sale | H30: 77421.9 | I30: 0.10012501 | P30: =G31 -> Asset sale | Q30: =H31 -> 77421.9 | R30: =I31 -> 0.10012501
G31: Asset sale | H31: 77421.9 | I31: 0.10012501 | P31: =G32 -> Advertising | Q31: =H32 -> 117541.05 | R31: =I32 -> 0.15200866
G32: Advertising | H32: 117541.05 | I32: 0.15200866 | P32: =G33 -> Company Website | Q32: =H33 -> 1225 | R32: =I33 -> 0.0015842177
G33: Company Website | H33: 1225 | I33: 0.0015842177 | P33: =G34 -> Facebook Page | Q33: =H34 -> 28378.64 | R33: =I34 -> 0.036700361
G34: Facebook Page | H34: 28378.64 | I34: 0.036700361 | P34: =G35 -> Google Ad | Q34: =H35 -> 27919.09 | R34: =I35 -> 0.036106053
G35: Google Ad | H35: 27919.09 | I35: 0.036106053 | P35: =G36 -> Television Ad | Q35: =H36 -> 31527.743 | R35: =I36 -> 0.040772903
G36: Television Ad | H36: 31527.743 | I36: 0.040772903 | P36: =G37 -> Youtube Channel | Q36: =H37 -> 28490.58 | R36: =I37 -> 0.036845126
G37: Youtube Channel | H37: 28490.58 | I37: 0.036845126
G38: Grand Total | H38: 773252.33 | I38: 1

Sheet dfgeog
A1: Year | B1: Country | C1: Amount | D1: Target
A2: 2020 | B2: Egypt | C2: 364236 | D2: 501558.2
A3: 2020 | B3: USA | C3: 197480 | D3: 360897.68
A4: 2020 | B4: Russia | C4: 187412 | D4: 227490.12
A5: 2020 | B5: United Kingdom | C5: 167840 | D5: 281795.8
A6: 2020 | B6: Brazil | C6: 126472 | D6: 206264.6
A7: 2020 | B7: Canada | C7: 125960 | D7: 202419.36
A8: 2021 | B8: Egypt | C8: 342724 | D8: 509978.04
A9: 2021 | B9: USA | C9: 238460 | D9: 280188.48
A10: 2021 | B10: Russia | C10: 231288 | D10: 209586.52
A11: 2021 | B11: United Kingdom | C11: 210228 | D11: 273633.36
A12: 2021 | B12: Canada | C12: 135984 | D12: 204158.24
A13: 2021 | B13: Brazil | C13: 128888 | D13: 275347.04
... A31: 2024 | B31: Brazil | C31: 62240 | D31: 90151.2
A33: Verde oscuro | B33: #070E0A
A34: Azul | B34: #194AFE
A35: Violeta oscuro | B35: #252253
A36: Lila | B36: #B349D1
A37: Turquesa | B37: #55D9FB

Sheet ptgeog
B2: Row Labels | C2: Sum of Amount | D2: Sum of Amount2 | J2: Sum of Amount | K2: Sum of Target | M2: X | N2: Y
B3: Egypt | C3: 364236 | D3: 0.31147255 | F3: =B3 -> Egypt | G3: =D3 -> 0.31147255 | H3: =IFERROR(C3,"") -> 364236 | J3: 1169400 | K3: 1780425.8 | M3: 0 | N3: 1
B4: USA | C4: 197480 | D4: 0.16887293 | F4: =B4 -> USA | G4: =D4 -> 0.16887293 | H4: =IFERROR(C4,"") -> 197480 | M4: =SIN(J6*2*PI()) -> 0.83341647 | N4: =COS(K6*2*PI()) -> -0.55264545
B5: Russia | C5: 187412 | D5: 0.16026338 | F5: =B5 -> Russia | G5: =D5 -> 0.16026338 | H5: =IFERROR(C5,"") -> 187412 | J5: Remaining | K5: Actual
B6: United Kingdom | C6: 167840 | D6: 0.14352659 | F6: =B6 -> United Kingdom | G6: =D6 -> 0.14352659 | H6: =IFERROR(C6,"") -> 167840 | J6: =100%-K6 -> 0.34319081 | K6: =GETPIVOTDATA("Sum of Amount",$J$3)/GETPIVOTDATA("Sum of Target",$K$3) -> 0.65680919
B7: Brazil | C7: 126472 | D7: 0.10815119 | F7: =B7 -> Brazil | G7: =D7 -> 0.10815119 | H7: =IFERROR(C7,"") -> 126472
B8: Canada | C8: 125960 | D8: 0.10771336 | F8: =B8 -> Canada | G8: =D8 -> 0.10771336 | H8: =IFERROR(C8,"") -> 125960
B9: Grand Total | C9: 1169400 | D9: 1
C11: Total Sales | D11: =GETPIVOTDATA("Sum of Amount",$B$2) -> 1169400
J12: Payroll Taxes | K12: Property Taxes | L12: Excise Taxes | M12: Total Taxes | N12: 1
C13: Highest | E13: Non Highest | J13: =(J14*D11) -> 107584.8 | K13: =(K14*D11) -> 86535.6 | L13: =(L14*D11) -> 72502.8 | M13: =(M14*D11) -> 266623.2
B14: Egypt | C14: =IF(B14=$B$3,"•","") -> • | D14: =IF(B14=$B$3,"•","") -> • | E14: =IF(B14=$B$3," ","•") | F14: =IF(B14=$B$3," ","•") | J14: 0.092 | K14: 0.074 | L14: 0.062 | M14: =SUM(J14:L14) -> 0.228 | N14: =100%-M14 -> 0.772
B15: USA | C15: =IF(B15=$B$3,"•","") | D15: =IF(B15=$B$3,"•","") | E15: =IF(B15=$B$3," ","•") -> • | F15: =IF(B15=$B$3," ","•") -> •
B16: Russia | C16: =IF(B16=$B$3,"•","") | D16: =IF(B16=$B$3,"•","") | E16: =IF(B16=$B$3," ","•") -> • | F16: =IF(B16=$B$3," ","•") -> •
B17: United Kingdom | C17: =IF(B17=$B$3,"•","") | D17: =IF(B17=$B$3,"•","") | E17: =IF(B17=$B$3," ","•") -> • | F17: =IF(B17=$B$3," ","•") -> •
B18: Canada | C18: =IF(B18=$B$3,"•","") | D18: =IF(B18=$B$3,"•","") | E18: =IF(B18=$B$3," ","•") -> • | F18: =IF(B18=$B$3," ","•") -> •
B19: Brazil | C19: =IF(B19=$B$3,"•","") | D19: =IF(B19=$B$3,"•","") | E19: =IF(B19=$B$3," ","•") -> • | F19: =IF(B19=$B$3," ","•") -> •
D20: =IF(B20=$B$3,"•","")

Sheet dfsales
A1: Order Number | B1: Year | C1: Month | D1: POS | E1: Payment Method | F1: Assembly Stage | G1: Registration Status | H1: Sale Status | I1: Delivery Type | J1: Amount | K1: Target
A2: AD01-9361 | B2: 2020 | C2: Apr | D2: Website | E2: Credit Card | F2: Order assembled | G2: Register Customer info | H2: Paid | I2: Shipment | J2: 350 | K2: 500.5
A3: AD01-9361 | B3: 2020 | C3: Apr | D3: Website | E3: Credit Card | F3: Order assembled | G3: Register Customer info | H3: Paid | I3: Shipment | J3: 344 | K3: 491.92
A4: AD01-9362 | B4: 2020 | C4: Apr | D4: Website | E4: Credit Card | F4: Order assembled | G4: Register Customer info | H4: Paid | I4: Download | J4: 236 | K4: 337.48
A5: AD01-9362 | B5: 2020 | C5: Apr | D5: Website | E5: Credit Card | F5: Order assembled | G5: Register Customer info | H5: Paid | I5: Download | J5: 284 | K5: 406.12
A6: AD01-9364 | B6: 2020 | C6: Apr | D6: Website | E6: Credit Card | F6: Order assembled | G6: Register Customer info | H6: Paid | I6: Download | J6: 238 | K6: 340.34
A7: AD01-9361 | B7: 2020 | C7: Apr | D7: Website | E7: Credit Card | F7: Order assembled | G7: Register Customer info | H7: Paid | I7: Download | J7: 280 | K7: 400.4
A8: AD01-9361 | B8: 2020 | C8: Apr | D8: Website | E8: Credit Card | F8: Order assembled | G8: Register Customer info | H8: Paid | I8: Download | J8: 208 | K8: 297.44
A9: AD01-9362 | B9: 2020 | C9: Apr | D9: Website | E9: Credit Card | F9: Order assembled | G9: Register Customer info | H9: Paid | I9: Shipment | J9: 354 | K9: 526.24
A10: AD01-9361 | B10: 2020 | C10: Apr | D10: Website | E10: Credit Card | F10: Order assembled | G10: Register Customer info | H10: Paid | I10: Shipment | J10: 348 | K10: 526.24
A11: AD01-9364 | B11: 2020 | C11: Apr | D11: Website | E11: Credit Card | F11: Order assembled | G11: Register Customer info | H11: Paid | I11: Shipment | J11: 342 | K11: 526.24
A12: AD01-9363 | B12: 2020 | C12: Apr | D12: Website | E12: Credit Card | F12: Order assembled | G12: Register Customer info | H12: Paid | I12: Download | J12: 677 | K12: 968.11
A13: AD01-9364 | B13: 2020 | C13: Apr | D13: Website | E13: Credit Card | F13: Order assembled | G13: Register Customer info | H13: Paid | I13: Download | J13: 710 | K13: 1015.3
... A3116: AD01-9362 | B3116: 2024 | C3116: Sep | D3116: Branches | E3116: Cash on Delivery | F3116: Cancelld | G3116: Non-Registered Customer info | H3116: Refunded | I3116: Branch | J3116: 173 | K3116: 247.39

Sheet ptsales
M1: │
B2: Sum of Target | C2: Sum of Amount | E2: Actual | F2: Target | G2: Label | I2: Row Labels | J2: Count of POS | M2: Line | N2: Empty circle | O2: Full circle | P2: Count
B3: 418243.54 | C3: 294032 | E3: =GETPIVOTDATA("Sum of Amount",$B$2)/GETPIVOTDATA("Sum of Target",$B$2) -> 0.70301624 | F3: =100%-E3 -> 0.29698376 | G3: =F3 -> 0.29698376 | I3: Website | J3: 622 | L3: Branches | M3: =IF(L3=$I$3,"│","") | N3: =IF(L3=$I$3,"○","") | O3: =IF(L3=$I$3,"","●") -> ● | P3: =IF(L3=$I$3,J3,"")
G4: =E3 -> 0.70301624 | I4: Branches | J4: 146 | L4: Website | M4: =IF(L4<>$I$4,"│","") -> │ | N4: =IF(L4<>$I$4,"○","") -> ○ | O4: =IF(L4=$I$4,"●","") | P4: =IF(L4<>$I$4,J4,"") -> 146
E5: X | F5: Y | I5: Grand Total | J5: 768
E6: 0 | F6: 1
E7: =SIN(E3*2*PI()) -> -0.95674174 | F7: =COS(F3*2*PI()) -> -0.29093856
I8: Row Labels | J8: Count of Payment Method | M8: Line | N8: Empty circle | O8: Full circle | P8: Count
I9: Credit Card | J9: 512 | L9: Credit Card | M9: =IF(L9=$I$9,"│","") -> │ | N9: =IF(L9=$I$9,"○","") -> ○ | O9: =IF(L9=$I$9,"","●") | P9: =IF(L9=$I$9,J9,"") -> 512
I10: Cash on Delivery | J10: 256 | L10: Cash on Delivery | M10: =IF(L10<>$I$10,"│","") | N10: =IF(L10<>$I$10,"○","") | O10: =IF(L10=$I$10,"●","") -> ● | P10: =IF(L10<>$I$10,J9,"")
I11: Grand Total | J11: 768
I14: Row Labels | J14: Count of Registration Status | M14: Line | N14: Empty circle | O14: Full circle | P14: Count
I15: Register Customer info | J15: 492 | L15: Register Customer info | M15: =IF(L15=$I$15,"│","") -> │ | N15: =IF(L15=$I$15,"○","") -> ○ | O15: =IF(L15=$I$15,"","●") | P15: =IF(L15=$I$15,J15,"") -> 492
I16: Non-Registered Customer info | J16: 276 | L16: Non-Registered Customer info | M16: =IF(L16<>$I$16,"│","") | N16: =IF(L16<>$I$16,"○","") | O16: =IF(L16=$I$16,"●","") -> ● | P16: =IF(L16<>$I$16,J16,"")
I17: Grand Total | J17: 768
C21: Sum of Amount | F21: Amount | I21: Row Labels | J21: Count of Delivery Type | L21: Row Labels | M21: Count of Sale Status | P21: Count
B22: Branch | C22: 100362 | E22: Branch | F22: =C22 -> 100362 | I22: Branch | J22: 215 | L22: Paid | M22: 0.81770833 | O22: Paid | P22: =M22 -> 0.81770833
B23: Download | C23: 72827 | E23: Download | F23: =C23 -> 72827 | I23: Download | J23: 214 | L23: Refunded | M23: 0.18229167 | O23: Refuned | P23: =M23 -> 0.18229167
B24: Shipment | C24: 120843 | E24: Shipment | F24: =C24 -> 120843 | I24: Shipment | J24: 339 | L24: Grand Total | M24: 1
B25: Grand Total | C25: 294032 | E25: Total | F25: =C25 -> 294032 | I25: Grand Total | J25: 768

Sheet Income Sources

Sheet Geographically

Sheet Sales Process
